pydtp/Client.py
pydtp/Handler.py
pydtp/Server.py
pydtp/__init__.py
pydtp/converters.py
pydtp-0.1.1.dist-info/METADATA
pydtp-0.1.1.dist-info/WHEEL
pydtp-0.1.1.dist-info/top_level.txt
pydtp-0.1.1.dist-info/RECORD
