Metadata-Version: 2.1
Name: pydtp
Version: 0.1.1
Summary: A simple protocol based on json representation of python dictionaries
Home-page: https://github.com/landerlini/pydtp
Author: Lucio Anderlini
Author-email: Lucio.Anderlini@fi.infn.it
License: UNKNOWN
Platform: UNKNOWN
Classifier: Programming Language :: Python :: 3
Classifier: License :: OSI Approved :: MIT License
Classifier: Operating System :: OS Independent
